smdl/__init__.py
smdl-0.0.1.dist-info/DESCRIPTION.rst
smdl-0.0.1.dist-info/METADATA
smdl-0.0.1.dist-info/RECORD
smdl-0.0.1.dist-info/WHEEL
smdl-0.0.1.dist-info/metadata.json
smdl-0.0.1.dist-info/top_level.txt
