Metadata-Version: 2.0
Name: smdl
Version: 0.0.1
Summary: A ML & DL lib
Home-page: http://githbu.com/spxcds/sdml
Author: spxcds
Author-email: spxcds@gmail.com
License: MIT
Platform: UNKNOWN
Classifier: Programming Language :: Python :: 2.7
Classifier: License :: OSI Approved :: MIT License
Classifier: Operating System :: OS Independent
